sinaraml_jupyter_host_ext/__init__.py
sinaraml_jupyter_host_ext/_version.py
sinaraml_jupyter_host_ext/handlers.py
sinaraml_jupyter_host_ext/public/index.html
sinaraml_jupyter_host_ext/tests/__init__.py
sinaraml_jupyter_host_ext/tests/test_handlers.py
sinaraml_jupyter_host_ext-2025.4.2.data/data/etc/jupyter/jupyter_server_config.d/sinaraml_jupyter_host_ext.json
sinaraml_jupyter_host_ext-2025.4.2.data/data/share/jupyter/labextensions/@sinaraml/sinaraml_jupyter_host_ext/package.json
sinaraml_jupyter_host_ext-2025.4.2.data/data/share/jupyter/labextensions/@sinaraml/sinaraml_jupyter_host_ext/static/675.58f8c9afc915e46dbd48.js
sinaraml_jupyter_host_ext-2025.4.2.data/data/share/jupyter/labextensions/@sinaraml/sinaraml_jupyter_host_ext/static/728.a249359cfaa14db2b512.js
sinaraml_jupyter_host_ext-2025.4.2.data/data/share/jupyter/labextensions/@sinaraml/sinaraml_jupyter_host_ext/static/remoteEntry.a6a5ea9f25659b690b24.js
sinaraml_jupyter_host_ext-2025.4.2.data/data/share/jupyter/labextensions/@sinaraml/sinaraml_jupyter_host_ext/static/style.js
sinaraml_jupyter_host_ext-2025.4.2.data/data/share/jupyter/labextensions/@sinaraml/sinaraml_jupyter_host_ext/static/third-party-licenses.json
sinaraml_jupyter_host_ext-2025.4.2.data/data/share/jupyter/labextensions/@sinaraml/sinaraml_jupyter_host_ext/install.json
sinaraml_jupyter_host_ext-2025.4.2.dist-info/METADATA
sinaraml_jupyter_host_ext-2025.4.2.dist-info/WHEEL
sinaraml_jupyter_host_ext-2025.4.2.dist-info/RECORD
